CHANGELOG.txt
LICENSE
MANIFEST.in
README.txt
setup.py
a_detect/AR_model.py
a_detect/Hierarchical_Interval_Halving.py
a_detect/Minimum_Variance_Index.py
a_detect/__init__.py
a_detect/bottoms_up.py
a_detect/interval_halving.py
a_detect/optimal_hyperparameter.py
a_detect.egg-info/PKG-INFO
a_detect.egg-info/SOURCES.txt
a_detect.egg-info/dependency_links.txt
a_detect.egg-info/requires.txt
a_detect.egg-info/top_level.txt