Metadata-Version: 2.1
Name: a-detect
Version: 0.0.3
Summary: bottom up segementation
Home-page: 
Author: aaron
Author-email: 
License: MIT
Keywords: segementation
Classifier: Development Status :: 5 - Production/Stable
Classifier: Intended Audience :: Education
Classifier: Operating System :: Microsoft :: Windows :: Windows 10
Classifier: License :: OSI Approved :: MIT License
Classifier: Programming Language :: Python :: 3
License-File: LICENSE
